devtransfer/__init__.py
devtransfer/_nbdev.py
devtransfer/core.py
plutopy_cli/__init__.py
plutopy_cli/_nbdev.py
plutopy_cli/core.py
plutopy_cli-0.0.1.dist-info/LICENSE
plutopy_cli-0.0.1.dist-info/METADATA
plutopy_cli-0.0.1.dist-info/WHEEL
plutopy_cli-0.0.1.dist-info/entry_points.txt
plutopy_cli-0.0.1.dist-info/top_level.txt
plutopy_cli-0.0.1.dist-info/RECORD
