Metadata-Version: 2.1
Name: plutopy-cli
Version: 0.0.1
Summary: On demand GPU-based jupyter notebook backends
Home-page: https://github.plutopy.com/plutopy/plutopy-cli/tree/main/
Author: Justin Mitchel
Author-email: plutopyproject@gmail.com
License: Apache Software License 2.0
Keywords: jupyter notebook,ipython,gpu
Platform: UNKNOWN
Classifier: Development Status :: 3 - Alpha
Classifier: Intended Audience :: Developers
Classifier: Natural Language :: English
Classifier: Programming Language :: Python :: 3.6
Classifier: Programming Language :: Python :: 3.7
Classifier: Programming Language :: Python :: 3.8
Classifier: Programming Language :: Python :: 3.9
Classifier: Programming Language :: Python :: 3.10
Classifier: License :: OSI Approved :: Apache Software License
Requires-Python: >=3.6
Requires-Dist: pip
Requires-Dist: packaging
Provides-Extra: dev
